octoeverywhere/__init__.py
octoeverywhere/octo.py
octoeverywhere/legacy/__init__.py
octoeverywhere/legacy/legacy.py
OctoEverywhereAPI-1.0.3.dist-info/LICENSE
OctoEverywhereAPI-1.0.3.dist-info/METADATA
OctoEverywhereAPI-1.0.3.dist-info/WHEEL
OctoEverywhereAPI-1.0.3.dist-info/top_level.txt
OctoEverywhereAPI-1.0.3.dist-info/RECORD
