Metadata-Version: 2.1
Name: OctoEverywhereAPI
Version: 1.0.3
Summary: A Unoffical API for OctoEverywhere
Home-page: https://github.com/mytja/OctoEverywhereAPI
Author: mytja
License: UNKNOWN
Platform: UNKNOWN
Classifier: Programming Language :: Python :: 3
Classifier: License :: OSI Approved :: MIT License
Classifier: Operating System :: OS Independent
Requires-Python: >=3
Requires-Dist: requests
